redasql/__init__.py
redasql/api_client.py
redasql/command.py
redasql/completer.py
redasql/constants.py
redasql/dto.py
redasql/exceptions.py
redasql/metacommand_executor.py
redasql/result_formatter.py
redasql/result_outputter.py
redasql/utils.py
redasql-2.7.4.dist-info/METADATA
redasql-2.7.4.dist-info/WHEEL
redasql-2.7.4.dist-info/entry_points.txt
redasql-2.7.4.dist-info/licenses/LICENSE
redasql-2.7.4.dist-info/RECORD
