Metadata-Version: 2.4
Name: redasql
Version: 2.7.4
Summary: 
License: MIT
License-File: LICENSE
Keywords: redash,sql
Author: denzow
Author-email: denzow@gmail.com
Requires-Python: >=3.8,<4.0
Classifier: Environment :: Console
Classifier: License :: OSI Approved :: MIT License
Classifier: Programming Language :: Python :: 3
Classifier: Programming Language :: Python :: 3.8
Classifier: Programming Language :: Python :: 3.9
Classifier: Programming Language :: Python :: 3.10
Classifier: Programming Language :: Python :: 3.11
Classifier: Programming Language :: Python :: 3.12
Classifier: Programming Language :: Python :: 3.13
Classifier: Programming Language :: Python :: 3.14
Classifier: Programming Language :: Python :: 3.7
Requires-Dist: prompt-toolkit (>=3.0.20,<4.0.0)
Requires-Dist: pyperclip (>=1.8.2,<2.0.0)
Requires-Dist: requests (>=2.26.0,<3.0.0)
Requires-Dist: tabulate (>=0.8.9,<0.9.0)
Project-URL: Homepage, https://github.com/denzow/redasql
Project-URL: Repository, https://github.com/denzow/redasql
